keplerio/__init__.py
keplerio-0.2.0.dist-info/licenses/LICENSE
keplerio-0.2.0.dist-info/METADATA
keplerio-0.2.0.dist-info/WHEEL
keplerio-0.2.0.dist-info/top_level.txt
keplerio-0.2.0.dist-info/RECORD
